pywebworker/__init__.py
pywebworker/pyworker.js
pywebworker/pyworker.py
pywebworker/worker.js
pywebworker/worker.py
pywebworker/worker_config.py
pywebworker-0.0.8.data/data/js/pyworker.js
pywebworker-0.0.8.data/data/js/worker.js
pywebworker-0.0.8.dist-info/LICENSE
pywebworker-0.0.8.dist-info/METADATA
pywebworker-0.0.8.dist-info/WHEEL
pywebworker-0.0.8.dist-info/top_level.txt
pywebworker-0.0.8.dist-info/RECORD
