Metadata-Version: 2.1
Name: pywebworker
Version: 0.0.8
Summary: Python tools for interacting with Web Workers in Pyodide
Home-page: https://github.com/masonlogan1/pywebworker
Author: malogan (Mason Logan)
Author-email: <dev@masonlogan.com>
License: UNKNOWN
Keywords: python,pyodide,web workers,web api
Platform: UNKNOWN
Classifier: Development Status :: 2 - Pre-Alpha
Classifier: Intended Audience :: Developers
Classifier: Programming Language :: Python :: 3
Classifier: Operating System :: Unix
Classifier: Operating System :: MacOS :: MacOS X
Classifier: Operating System :: Microsoft :: Windows
License-File: LICENSE
